ms_recognizers_number/__init__.py
ms_recognizers_number/culture.py
ms_recognizers_number/number/__init__.py
ms_recognizers_number/number/cjk_parsers.py
ms_recognizers_number/number/constants.py
ms_recognizers_number/number/extractors.py
ms_recognizers_number/number/models.py
ms_recognizers_number/number/number_options.py
ms_recognizers_number/number/number_recognizer.py
ms_recognizers_number/number/parser_factory.py
ms_recognizers_number/number/parsers.py
ms_recognizers_number/number/utilities.py
ms_recognizers_number/number/chinese/__init__.py
ms_recognizers_number/number/chinese/extractors.py
ms_recognizers_number/number/chinese/parsers.py
ms_recognizers_number/number/dutch/__init__.py
ms_recognizers_number/number/dutch/extractors.py
ms_recognizers_number/number/dutch/parsers.py
ms_recognizers_number/number/english/__init__.py
ms_recognizers_number/number/english/extractors.py
ms_recognizers_number/number/english/parsers.py
ms_recognizers_number/number/french/__init__.py
ms_recognizers_number/number/french/extractors.py
ms_recognizers_number/number/french/parsers.py
ms_recognizers_number/number/german/__init__.py
ms_recognizers_number/number/german/extractors.py
ms_recognizers_number/number/german/parsers.py
ms_recognizers_number/number/italian/__init__.py
ms_recognizers_number/number/italian/extractors.py
ms_recognizers_number/number/italian/parsers.py
ms_recognizers_number/number/japanese/__init__.py
ms_recognizers_number/number/japanese/extractors.py
ms_recognizers_number/number/japanese/parsers.py
ms_recognizers_number/number/portuguese/__init__.py
ms_recognizers_number/number/portuguese/extractors.py
ms_recognizers_number/number/portuguese/parsers.py
ms_recognizers_number/number/spanish/__init__.py
ms_recognizers_number/number/spanish/extractors.py
ms_recognizers_number/number/spanish/parsers.py
ms_recognizers_number/resources/__init__.py
ms_recognizers_number/resources/base_numbers.py
ms_recognizers_number/resources/chinese_numeric.py
ms_recognizers_text_number-1.0.0.1.dist-info/METADATA
ms_recognizers_text_number-1.0.0.1.dist-info/WHEEL
ms_recognizers_text_number-1.0.0.1.dist-info/top_level.txt
ms_recognizers_text_number-1.0.0.1.dist-info/RECORD
